min_renovasjon/__init__.py
min_renovasjon/const.py
min_renovasjon/minrenovasjon.py
min_renovasjon-0.1.2.dist-info/LICENSE
min_renovasjon-0.1.2.dist-info/WHEEL
min_renovasjon-0.1.2.dist-info/METADATA
min_renovasjon-0.1.2.dist-info/RECORD
